numerbay/__init__.py
numerbay/cli.py
numerbay/numerbay.py
numerbay/utils.py
numerbay-0.2.4.dist-info/LICENSE
numerbay-0.2.4.dist-info/METADATA
numerbay-0.2.4.dist-info/WHEEL
numerbay-0.2.4.dist-info/entry_points.txt
numerbay-0.2.4.dist-info/top_level.txt
numerbay-0.2.4.dist-info/RECORD
