Metadata-Version: 2.1
Name: numerbay
Version: 0.2.4
Summary: Programmatic interaction with numerbay.ai - the Numerai community marketplace
Home-page: https://github.com/councilofelders/numerbay-api
Maintainer: numerbay
Maintainer-email: admin@numerbay.ai
License: MIT License
Project-URL: Documentation, https://docs.numerbay.ai/
Platform: OS Independent
Classifier: Development Status :: 3 - Alpha
Classifier: Environment :: Console
Classifier: Intended Audience :: Science/Research
Classifier: License :: OSI Approved :: MIT License
Classifier: Operating System :: OS Independent
Classifier: Programming Language :: Python
Classifier: Programming Language :: Python :: 3
Classifier: Topic :: Scientific/Engineering
Requires-Dist: requests
Requires-Dist: pytz
Requires-Dist: python-dateutil
Requires-Dist: tqdm (>=4.29.1)
Requires-Dist: click (>=7.0)
Requires-Dist: pandas (>=1.1.0)
Requires-Dist: pynacl
